evariste/__init__.py
evariste/__main__.py
evariste/builder.py
evariste/cache.py
evariste/errors.py
evariste/hooks.py
evariste/setup.py
evariste/shared.py
evariste/tree.py
evariste/utils.py
evariste/evs/__init__.py
evariste/evs/__main__.py
evariste/evs/cache/__init__.py
evariste/evs/cache/__main__.py
evariste/evs/compile/__init__.py
evariste/evs/compile/__main__.py
evariste/evs/compile/options.py
evariste/evs/plugins/__init__.py
evariste/evs/plugins/__main__.py
evariste/plugins/__init__.py
evariste/plugins/changed.py
evariste/plugins/copy.py
evariste/plugins/debug.py
evariste/plugins/logging.py
evariste/plugins/tree.py
evariste/plugins/action/__init__.py
evariste/plugins/action/autocommand.py
evariste/plugins/action/cached.py
evariste/plugins/action/command.py
evariste/plugins/action/make.py
evariste/plugins/action/nothing.py
evariste/plugins/renderer/__init__.py
evariste/plugins/renderer/text.py
evariste/plugins/renderer/html/__init__.py
evariste/plugins/renderer/html/data/templates/tree.html
evariste/plugins/renderer/html/data/templates/file/default.html
evariste/plugins/renderer/html/data/templates/file/image.html
evariste/plugins/renderer/html/file/__init__.py
evariste/plugins/renderer/html/file/image.py
evariste/plugins/renderer/html/readme/__init__.py
evariste/plugins/renderer/html/readme/mdwn.py
evariste/plugins/renderer/html/readme/rst.py
evariste/plugins/renderer/htmlplus/__init__.py
evariste/plugins/renderer/htmlplus/data/static/COPYING
evariste/plugins/renderer/htmlplus/data/static/application-x-zerosize.png
evariste/plugins/renderer/htmlplus/data/static/dialog-error.png
evariste/plugins/renderer/htmlplus/data/static/dialog-ok-apply.png
evariste/plugins/renderer/htmlplus/data/static/file.png
evariste/plugins/renderer/htmlplus/data/static/folder-open.png
evariste/plugins/renderer/htmlplus/data/static/folder.png
evariste/plugins/renderer/htmlplus/data/static/lgpl-3.0.txt
evariste/plugins/renderer/htmlplus/data/static/tree.css
evariste-1.3.0.dist-info/AUTHORS
evariste-1.3.0.dist-info/LICENSE
evariste-1.3.0.dist-info/METADATA
evariste-1.3.0.dist-info/WHEEL
evariste-1.3.0.dist-info/entry_points.txt
evariste-1.3.0.dist-info/top_level.txt
evariste-1.3.0.dist-info/RECORD
