Metadata-Version: 2.1
Name: evariste
Version: 1.3.0
Summary: Publish annoted and compiled directory tree.
Home-page: http://framagit.org/spalax/evariste
Author: Louis Paternault
Author-email: spalax@gresille.org
License: AGPLv3 or any later version
Project-URL: Documentation, http://evariste.readthedocs.io
Project-URL: Source, https://framagit.org/spalax/evariste
Project-URL: Tracker, https://framagit.org/spalax/evariste/issues
Keywords: compilation vcs publish html
Classifier: Development Status :: 5 - Production/Stable
Classifier: Intended Audience :: End Users/Desktop
Classifier: Environment :: Console
Classifier: License :: OSI Approved :: GNU Affero General Public License v3 or later (AGPLv3+)
Classifier: Programming Language :: Python :: 3 :: Only
Classifier: Programming Language :: Python :: 3
Classifier: Programming Language :: Python :: 3.8
Classifier: Programming Language :: Python :: 3.9
Classifier: Programming Language :: Python :: 3.10
Classifier: Programming Language :: Python :: 3.11
Classifier: Programming Language :: Python :: 3.12
Classifier: Programming Language :: Python :: 3.13
Classifier: Programming Language :: Python
Classifier: Topic :: Software Development :: Build Tools
Requires-Python: <4,>=3.8
License-File: LICENSE
License-File: AUTHORS
Requires-Dist: argdispatch
Requires-Dist: jinja2>=3
Requires-Dist: docutils
Requires-Dist: gitpython
Requires-Dist: markdown
Requires-Dist: rich
Requires-Dist: unidecode
